kanina/__init__.py
kanina/calculator.py
kanina-0.0.1.dist-info/LICENSE
kanina-0.0.1.dist-info/WHEEL
kanina-0.0.1.dist-info/METADATA
kanina-0.0.1.dist-info/RECORD
