Metadata-Version: 2.1
Name: kanina
Version: 0.0.1
Summary: An simple calculator package
Author: Henrikas
Author-email: henrikass@yahoo.com
Requires-Python: >=3.8
Classifier: License :: OSI Approved :: MIT License
